graphite/__init__.py
graphite/create_model.py
graphite/dataset.py
graphite/empty.json
graphite/graphite.py
graphite/image_processor.py
graphite/latex_list.py
graphite/latex_tokenizer.py
graphite/tree_utils.py
graphite_math-0.1.13.dist-info/licenses/LICENSE.txt
graphite_math-0.1.13.dist-info/METADATA
graphite_math-0.1.13.dist-info/WHEEL
graphite_math-0.1.13.dist-info/top_level.txt
graphite_math-0.1.13.dist-info/RECORD
